<frame id="12810:80161" name="❖ Icons">
<text id="12810:80201" name="Header" characters="Header" />
<symbol id="10590:96152" name="report-box" />
<symbol id="10590:96155" name="report-box-fill" />
<symbol id="10590:96145" name="folder" />
<symbol id="10590:96148" name="folder-fill" />
<symbol id="10590:96159" name="code" />
<symbol id="10590:96162" name="code-fill" />
<symbol id="10590:96166" name="image" />
<symbol id="10590:96169" name="image-fill" />
<symbol id="10590:96173" name="label" />
<symbol id="10590:96176" name="label-fill" />
<symbol id="10590:96180" name="document" />
<symbol id="10590:96183" name="document-fill" />
<symbol id="10590:96187" name="add-tag" />
<symbol id="10590:96190" name="add-tag-fill" />
<symbol id="209:2810" name="article" />
<symbol id="209:2914" name="article_shortcut" />
<symbol id="209:2911" name="article_person" />
<symbol id="209:2912" name="convert_to_text" />
<symbol id="209:2917" name="docs" />
<symbol id="209:2910" name="news" />
<symbol id="209:2909" name="notes" />
<symbol id="265:30479" name="sticky_note" />
<symbol id="265:30487" name="sticky_note_2" />
<symbol id="10590:96204" name="person" />
<symbol id="10590:96207" name="person-fill" />
<symbol id="11042:100728" name="apps-user management-fill" />
<symbol id="11042:100715" name="apps-user management" />
<symbol id="10590:96211" name="person-add" />
<symbol id="10590:96214" name="person-add-fill" />
<symbol id="10590:96218" name="account" />
<symbol id="10590:96221" name="account-fill" />
<symbol id="10590:96230" name="shopping" />
<symbol id="10590:96233" name="shopping-fill" />
<symbol id="10590:96240" name="savings" />
<symbol id="10590:96237" name="savings-fill" />
<symbol id="227:28015" name="money_bag" />
<symbol id="2024:19137" name="credit-card" />
<symbol id="10590:96267" name="format-bold" />
<symbol id="10590:96270" name="format-list-bulleted" />
<symbol id="10590:96273" name="format-align-center" />
<symbol id="10590:96276" name="format-align-left" />
<symbol id="288:11910" name="format_list_numbered" />
<symbol id="10590:96279" name="format-align-right" />
<symbol id="10590:96282" name="format-underlined" />
<symbol id="10590:96285" name="link" />
<symbol id="10590:96288" name="data-object" />
<symbol id="10590:96291" name="text" />
<symbol id="288:11880" name="format_italic" />
<symbol id="288:11888" name="strikethrough_s" />
<symbol id="10590:96297" name="drag-indicator" />
<symbol id="10590:96300" name="sort" />
<symbol id="10590:96306" name="search" />
<symbol id="10590:96309" name="check" />
<symbol id="10590:96312" name="minus" />
<symbol id="10590:96316" name="lock" />
<symbol id="10590:96319" name="lock-fill" />
<symbol id="10590:96322" name="calendar" />
<symbol id="10590:96325" name="calendar-fill" />
<symbol id="10590:96329" name="edit" />
<symbol id="10590:96332" name="edit-fill" />
<symbol id="10590:96345" name="menu" />
<symbol id="10590:96339" name="home" />
<symbol id="10590:96342" name="home-fill" />
<symbol id="10834:90631" name="apps" />
<symbol id="10590:96351" name="equalizer" />
<symbol id="10590:96354" name="settings" />
<symbol id="10590:96364" name="chevron-left" />
<symbol id="10590:96367" name="chevron-right" />
<symbol id="10590:96370" name="chevron-up" />
<symbol id="10590:96373" name="chevron-down" />
<symbol id="10590:96376" name="arrow-drop-down" />
<symbol id="10590:96379" name="arrow-drop-up" />
<symbol id="10590:96382" name="arrow-drop-left" />
<symbol id="10590:96385" name="arrow-drop-right" />
<symbol id="10590:96388" name="arrow-forward" />
<symbol id="10590:96391" name="arrow-upward" />
<symbol id="10590:96394" name="arrow-downward" />
<symbol id="10590:96397" name="arrow-backward" />
<symbol id="10590:96400" name="log-in" />
<symbol id="10590:96403" name="log-out" />
<symbol id="10590:96406" name="view-new-window" />
<symbol id="13881:232" name="more-vert" />
<symbol id="13881:239" name="more-horiz" />
<symbol id="14691:21851" name="sort-default" />
<symbol id="10590:96419" name="theme" />
<symbol id="10590:96422" name="theme-fill" />
<symbol id="10590:96446" name="dollar" />
<symbol id="10590:96449" name="dollar-fill" />
<symbol id="10590:96425" name="application" />
<symbol id="10590:96428" name="application-fill" />
<symbol id="10590:96348" name="deployed-code" />
<symbol id="10682:92717" name="primary-color" />
<symbol id="10682:92668" name="tag" />
<symbol id="10682:92767" name="logo-fill" />
<symbol id="10682:92780" name="logo" />
<symbol id="10590:96442" name="mail" />
<symbol id="10590:96439" name="mail-fill" />
<symbol id="10590:96456" name="timer" />
<symbol id="10590:96459" name="timer-filled" />
<symbol id="10590:96463" name="tooltip-info" />
<symbol id="10590:96466" name="tooltip-info-filled" />
<symbol id="10590:96470" name="error" />
<symbol id="10590:96473" name="error-fill" />
<symbol id="10590:96477" name="circle-check" />
<symbol id="10590:96480" name="circle-check-fill" />
<symbol id="10590:96483" name="help" />
<symbol id="10590:96486" name="help-fill" />
<symbol id="10590:96490" name="camera" />
<symbol id="10590:96493" name="camera-fill" />
<symbol id="10590:96497" name="warning" />
<symbol id="10590:96500" name="warning-fill" />
<symbol id="10590:96504" name="pending" />
<symbol id="10590:96507" name="pending-fill" />
<symbol id="10590:96511" name="tips" />
<symbol id="10590:96514" name="tips-fill" />
<symbol id="10590:96518" name="text-snippet" />
<symbol id="10590:96521" name="text-snippet-fill" />
<symbol id="10590:96524" name="thumb-down" />
<symbol id="10590:96527" name="thumb-up" />
<symbol id="14614:1228" name="dangerous" />
<symbol id="10687:93036" name="lightbulb" />
<symbol id="10687:93035" name="lightbulb-fill" />
<symbol id="209:2928" name="verified" />
<symbol id="10590:96536" name="plus" />
<symbol id="10590:96540" name="circle-add" />
<symbol id="10590:96543" name="circle-add-fill" />
<symbol id="10590:96547" name="send" />
<symbol id="10590:96550" name="send-fill" />
<symbol id="10590:96554" name="circle-denied" />
<symbol id="10590:96557" name="circle-denied-fill" />
<symbol id="10590:96560" name="upload-cloud-fill" />
<symbol id="10590:96563" name="upload-cloud" />
<symbol id="10590:96567" name="bookmark" />
<symbol id="10590:96570" name="bookmark-fill" />
<symbol id="10590:96574" name="visibility-on" />
<symbol id="10590:96577" name="visibility-on-fill" />
<symbol id="10590:96581" name="visibility-off" />
<symbol id="10590:96584" name="visibility-off-fill" />
<symbol id="10590:96588" name="delete" />
<symbol id="10590:96591" name="delete-fill" />
<symbol id="10590:96595" name="map-pin" />
<symbol id="10590:96598" name="map-pin-fill" />
<symbol id="10590:96602" name="copy" />
<symbol id="10590:96605" name="copy-fill" />
<symbol id="10590:96609" name="expand-circle-down" />
<symbol id="10590:96612" name="expand-circle-down-fill" />
<symbol id="10590:96616" name="expand-circle-up" />
<symbol id="10590:96619" name="expand-circle-up-fill" />
<symbol id="10590:96622" name="download" />
<symbol id="10590:96625" name="upload" />
<symbol id="10590:96628" name="upload-fill" />
<symbol id="10590:96631" name="download-fill" />
<symbol id="10590:96637" name="unfold-less" />
<symbol id="10590:96640" name="unfold-more" />
<symbol id="10798:90567" name="collapse" />
<symbol id="10798:90574" name="expand" />
<symbol id="10590:96644" name="chat" />
<symbol id="10590:96647" name="chat-fill" />
<symbol id="11006:95709" name="message" />
<symbol id="10590:96650" name="play-arrow" />
<symbol id="10837:93543" name="circle" />
<symbol id="10935:93194" name="stack" />
<symbol id="10590:96358" name="notifications" />
<symbol id="10590:96361" name="notifications-fill" />
<symbol id="10590:96409" name="close" />
<symbol id="10590:96412" name="expand-sheet" />
<symbol id="10685:96973" name="collapse-sheet" />
<symbol id="11089:96091" name="bug-report" />
<symbol id="11479:21651" name="history" />
<symbol id="12665:156935" name="stethoscope" />
<symbol id="14599:29956" name="variable-add" />
<symbol id="14599:29946" name="fields" />
<symbol id="14489:372" name="call" />
<symbol id="14614:30766" name="contract-edit" />
<symbol id="14613:860" name="passkey" />
<symbol id="11089:96098" name="brand-awareness" />
<symbol id="10685:94674" name="id-verify" />
<symbol id="14556:29942" name="credit-worthy" />
<symbol id="10685:94735" name="eligibility-rule" />
<symbol id="2373:206" name="function" />
<symbol id="14575:29873" name="school" />
<symbol id="10590:96634" name="restart-alt" />
<symbol id="14797:1594" name="mark-email-unread" />
<symbol id="14869:1108" name="toggle-on" />
<symbol id="14882:4931" name="percent-input" />
<symbol id="14882:5108" name="dollar-input" />
<symbol id="14903:31773" name="security" />
<symbol id="14917:32527" name="brightness" />
<symbol id="2331:5235" name="dot-indicator" />
<symbol id="14927:32553" name="science" />
<symbol id="15108:1252" name="shield-person" />
<symbol id="147:5656" name="numbers" />
<symbol id="151:15876" name="discover_tune" />
<symbol id="153:15979" name="drag-handle" />
<symbol id="105:4619" name="swap_vert" />
<symbol id="209:2916" name="margin" />
<symbol id="209:2908" name="page_footer" />
<symbol id="226:28006" name="storefront" />
<symbol id="226:28005" name="shopping_bag_speed" />
<symbol id="233:28027" name="emergency_home" />
<symbol id="233:28038" name="energy_program_saving" />
<symbol id="233:28045" name="gite" />
<symbol id="233:28057" name="in_home_mode" />
<symbol id="233:28064" name="nest_eco_leaf" />
<symbol id="233:28076" name="roofing" />
<symbol id="233:28087" name="productivity" />
<symbol id="233:28094" name="acute" />
<symbol id="243:28336" name="flag_2" />
<symbol id="243:28344" name="flag" />
<symbol id="243:28352" name="siren" />
<symbol id="243:28364" name="priority" />
<symbol id="264:30471" name="attachment" />
<symbol id="2029:20909" name="cake" />
<symbol id="2032:210" name="mic" />
<symbol id="2033:2530" name="dock_to_left" />
<symbol id="2033:2550" name="crop_square" />
<symbol id="2033:2548" name="chips" />
<symbol id="2033:2557" name="view_kanban" />
<symbol id="13179:248" name="travel_explore" />
<symbol id="2033:2566" name="account_balance" />
<symbol id="2033:2578" name="app_spark" />
<symbol id="2033:2593" name="kid_star" />
<symbol id="2033:2601" name="settings_backup_restore" />
<symbol id="2033:2620" name="forward_media" />
<symbol id="2033:2628" name="frame_spark" />
<symbol id="2033:2646" name="cottage" />
<symbol id="2033:2654" name="thermostat_carbon" />
<symbol id="2033:2666" name="adjust" />
<symbol id="2033:2673" name="rotate_left" />
<symbol id="2033:2685" name="reply" />
<symbol id="2033:2692" name="play_circle" />
<symbol id="2033:2700" name="stop_circle" />
<symbol id="2033:2708" name="flip" />
<symbol id="2033:2716" name="scan" />
<symbol id="2033:2724" name="text_compare" />
<symbol id="2033:2732" name="stylus_note" />
<symbol id="2033:2740" name="stylus_highlighter" />
<symbol id="2033:2764" name="percent_discount" />
<symbol id="2033:2771" name="crown" />
<symbol id="2033:2779" name="celebration" />
<symbol id="2033:2787" name="release_alert" />
<symbol id="2033:2795" name="schedule" />
<symbol id="2033:2815" name="laptop_mac" />
<symbol id="2033:2822" name="laptop_windows" />
<symbol id="2033:2830" name="jamboard_kiosk" />
<symbol id="2033:2844" name="deblur" />
<symbol id="2033:2872" name="mobile_2" />
<symbol id="2034:211" name="thought" />
<symbol id="2035:2373" name="check_circle_unread" />
<symbol id="2035:2380" name="circle_circle" />
<symbol id="2035:2387" name="arrow-circle-up" />
<symbol id="2050:305" name="airport_shuttle" />
<symbol id="2050:313" name="directions_car" />
<symbol id="2050:327" name="delivery_truck_speed" />
<symbol id="2050:335" name="emoji_objects" />
<symbol id="2050:343" name="percent" />
<symbol id="2050:366" name="stylus_fountain_pen" />
<symbol id="2050:374" name="checkbook" />
<symbol id="2083:1412" name="border_all" />
<symbol id="2083:1415" name="table" />
<symbol id="2085:3752" name="motion_photos_paused" />
<symbol id="2085:3755" name="motion_play" />
<symbol id="2085:11725" name="table-fill" />
<symbol id="2087:11733" name="dock_to_bottom" />
<symbol id="2087:11741" name="dock_to_right" />
<symbol id="2087:11749" name="first_page" />
<symbol id="2087:11787" name="new_window" />
<symbol id="2146:429" name="triangle_up" />
<symbol id="2146:438" name="triangle_down" />
<symbol id="2146:445" name="alt_route" />
<symbol id="2146:453" name="arrow_split" />
<symbol id="2333:27611" name="comment" />
<symbol id="2362:289" name="wand_stars" />
<symbol id="2435:3557" name="cloud_download" />
<symbol id="2435:3564" name="downloading" />
<symbol id="2439:3307" name="database" />
</frame>
